Metadata-Version: 2.1
Name: bing-search-scraper
Version: 1.0.0
Summary: A python library to scrape bing search result
Home-page: UNKNOWN
Author: DataKund
Author-email: datakund@gmail.com
License: Apache License 2.0
Keywords: bing python bot_studio automation search scraper
Platform: UNKNOWN
License-File: LICENSE
